phrenology/__init__.py
phrenology/main.py
phrenology/common/__init__.py
phrenology/common/output.py
phrenology/common/output_template.py
phrenology/component/__init__.py
phrenology/component/header.py
phrenology/registry/__init__.py
phrenology/registry/headers.py
phrenology/registry/owasp-header-dictionary.py
phrenology-0.1.2.dist-info/LICENSE.txt
phrenology-0.1.2.dist-info/METADATA
phrenology-0.1.2.dist-info/WHEEL
phrenology-0.1.2.dist-info/top_level.txt
phrenology-0.1.2.dist-info/RECORD
