Metadata-Version: 2.1
Name: phrenology
Version: 0.1.2
Summary: Phrenology is a lightweight extendable and scalable tool for inspecting security headers in responses from webservers.  This project is striving to use as few non-standard installed python libraries as possible while maintaining as much functionality as possible.
Home-page: https://github.com/f8al/phrenology
Author: SecurityShrimp
Author-email: SecurityShrimp <SecurityShrimp@proton.me>
Project-URL: Homepage, https://github.com/f8al/phrenology
License-File: LICENSE.txt
